Workbook

Sheet README
A1: All-in-One Printer Firmware QA — QA Manual Test Pack
A3: Purpose | B3: Provide reusable sample manual test cases for printer firmware, copy/print/scan workflows, network connectivity, configuration, reliability, monitoring, security, and end-to-end validation.
A4: How to use | B4: Open each module sheet and update Status and Notes during execution. Summary KPIs and module counts refresh automatically.
A5: Important note | B5: These are sample QA scenarios for portfolio use and should be tailored to your target printer model, firmware branch, supported protocols, hardware options, service tools, and release criteria.
A6: Default status | B6: Not Run
A7: Default priority | B7: High
A8: Primary domain | B8: Firmware QA / Embedded Systems / All-in-One Printer
A10: Official reference sources
A11: IPP Everywhere | B11: https://www.pwg.org/ipp/everywhere.html | C11: Driverless network/USB printing standard and capability/discovery reference
A12: How to Use IPP | B12: https://www.pwg.org/ipp/ippguide.html | C12: IPP objects, capabilities, printer state, and job monitoring guidance
A13: WS-Print v1.1 | B13: https://learn.microsoft.com/en-us/windows-hardware/drivers/print/ws-print-v1-1 | C13: Microsoft overview of Web Services for Devices printing protocols
A14: WSD Scan Verify | B14: https://learn.microsoft.com/en-us/windows-hardware/test/hlk/testref/ac904c9d-4117-4d89-ae72-476aa618255c | C14: Manual verification guidance for WSD scan protocol behavior
A15: Printer MIB v2 (RFC 3805) | B15: https://datatracker.ietf.org/doc/html/rfc3805 | C15: Device management and printer status object model reference
A16: IPP Scan Service | B16: https://ftp.pwg.org/pub/pwg/candidates/cs-ippscan10-20140918-5100.17.pdf | C16: Scan service operations and semantics over IPP

Sheet Summary
A1: All-in-One Printer Firmware QA Tracker
A2: Manual QA test suite for printer firmware and embedded system validation using the same multi-tab execution-tracker structure as the prior Data / ETL portfolio packs.
A4: Workbook Controls
A5: Default Status | B5: Not Run
A6: Default Priority | B6: High
A7: Portfolio Owner | B7: Ramon Tan Jr.
A8: Primary Domain | B8: Firmware QA / Embedded Systems / All-in-One Printer
A10: Module Coverage
A11: Module | B11: Sheet Name | C11: Total Cases | D11: High Priority | E11: Negative Cases | F11: Automation Candidates
A12: Print Functionality | B12: 10_Print_Functionality | C12: =COUNTA('10_Print_Functionality'!A:A)-2 -> 6 | D12: =COUNTIF('10_Print_Functionality'!H:H,"High")+COUNTIF('10_Print_Functionality'!H:H,"Critical") -> 6 | E12: =COUNTIF('10_Print_Functionality'!I:I,"Negative") -> 1 | F12: =COUNTIF('10_Print_Functionality'!J:J,"Yes")+COUNTIF('10_Print_Functionality'!J:J,"Later") -> 6
A13: Copy Functionality | B13: 20_Copy_Functionality | C13: =COUNTA('20_Copy_Functionality'!A:A)-2 -> 6 | D13: =COUNTIF('20_Copy_Functionality'!H:H,"High")+COUNTIF('20_Copy_Functionality'!H:H,"Critical") -> 4 | E13: =COUNTIF('20_Copy_Functionality'!I:I,"Negative") -> 1 | F13: =COUNTIF('20_Copy_Functionality'!J:J,"Yes")+COUNTIF('20_Copy_Functionality'!J:J,"Later") -> 5
A14: Scan Functionality | B14: 30_Scan_Functionality | C14: =COUNTA('30_Scan_Functionality'!A:A)-2 -> 6 | D14: =COUNTIF('30_Scan_Functionality'!H:H,"High")+COUNTIF('30_Scan_Functionality'!H:H,"Critical") -> 5 | E14: =COUNTIF('30_Scan_Functionality'!I:I,"Negative") -> 1 | F14: =COUNTIF('30_Scan_Functionality'!J:J,"Yes")+COUNTIF('30_Scan_Functionality'!J:J,"Later") -> 6
A15: Network Connectivity | B15: 40_Network_Connectivity | C15: =COUNTA('40_Network_Connectivity'!A:A)-2 -> 6 | D15: =COUNTIF('40_Network_Connectivity'!H:H,"High")+COUNTIF('40_Network_Connectivity'!H:H,"Critical") -> 5 | E15: =COUNTIF('40_Network_Connectivity'!I:I,"Negative") -> 3 | F15: =COUNTIF('40_Network_Connectivity'!J:J,"Yes")+COUNTIF('40_Network_Connectivity'!J:J,"Later") -> 2
A16: Firmware & Configuration | B16: 50_Firmware_Configuration | C16: =COUNTA('50_Firmware_Configuration'!A:A)-2 -> 6 | D16: =COUNTIF('50_Firmware_Configuration'!H:H,"High")+COUNTIF('50_Firmware_Configuration'!H:H,"Critical") -> 5 | E16: =COUNTIF('50_Firmware_Configuration'!I:I,"Negative") -> 2 | F16: =COUNTIF('50_Firmware_Configuration'!J:J,"Yes")+COUNTIF('50_Firmware_Configuration'!J:J,"Later") -> 2
A17: Paper Handling & Media | B17: 60_Paper_Handling_Media | C17: =COUNTA('60_Paper_Handling_Media'!A:A)-2 -> 6 | D17: =COUNTIF('60_Paper_Handling_Media'!H:H,"High")+COUNTIF('60_Paper_Handling_Media'!H:H,"Critical") -> 3 | E17: =COUNTIF('60_Paper_Handling_Media'!I:I,"Negative") -> 3 | F17: =COUNTIF('60_Paper_Handling_Media'!J:J,"Yes")+COUNTIF('60_Paper_Handling_Media'!J:J,"Later") -> 3
A18: UI & Control Panel | B18: 70_UI_Control_Panel | C18: =COUNTA('70_UI_Control_Panel'!A:A)-2 -> 5 | D18: =COUNTIF('70_UI_Control_Panel'!H:H,"High")+COUNTIF('70_UI_Control_Panel'!H:H,"Critical") -> 4 | E18: =COUNTIF('70_UI_Control_Panel'!I:I,"Negative") -> 0 | F18: =COUNTIF('70_UI_Control_Panel'!J:J,"Yes")+COUNTIF('70_UI_Control_Panel'!J:J,"Later") -> 3
A19: Security & Access | B19: 80_Security_Access | C19: =COUNTA('80_Security_Access'!A:A)-2 -> 5 | D19: =COUNTIF('80_Security_Access'!H:H,"High")+COUNTIF('80_Security_Access'!H:H,"Critical") -> 4 | E19: =COUNTIF('80_Security_Access'!I:I,"Negative") -> 0 | F19: =COUNTIF('80_Security_Access'!J:J,"Yes")+COUNTIF('80_Security_Access'!J:J,"Later") -> 3
A20: Monitoring & Alerts | B20: 90_Monitoring_Alerts | C20: =COUNTA('90_Monitoring_Alerts'!A:A)-2 -> 5 | D20: =COUNTIF('90_Monitoring_Alerts'!H:H,"High")+COUNTIF('90_Monitoring_Alerts'!H:H,"Critical") -> 3 | E20: =COUNTIF('90_Monitoring_Alerts'!I:I,"Negative") -> 0 | F20: =COUNTIF('90_Monitoring_Alerts'!J:J,"Yes")+COUNTIF('90_Monitoring_Alerts'!J:J,"Later") -> 5
A21: Performance & Reliability | B21: 100_Performance_Reliability | C21: =COUNTA('100_Performance_Reliability'!A:A)-2 -> 5 | D21: =COUNTIF('100_Performance_Reliability'!H:H,"High")+COUNTIF('100_Performance_Reliability'!H:H,"Critical") -> 4 | E21: =COUNTIF('100_Performance_Reliability'!I:I,"Negative") -> 0 | F21: =COUNTIF('100_Performance_Reliability'!J:J,"Yes")+COUNTIF('100_Performance_Reliability'!J:J,"Later") -> 3
A22: End-to-End | B22: 110_E2E | C22: =COUNTA('110_E2E'!A:A)-2 -> 4 | D22: =COUNTIF('110_E2E'!H:H,"High")+COUNTIF('110_E2E'!H:H,"Critical") -> 4 | E22: =COUNTIF('110_E2E'!I:I,"Negative") -> 0 | F22: =COUNTIF('110_E2E'!J:J,"Yes")+COUNTIF('110_E2E'!J:J,"Later") -> 1
A23: Total | C23: =SUM(C12:C22) -> 60 | D23: =SUM(D12:D22) -> 47 | E23: =SUM(E12:E22) -> 11 | F23: =SUM(F12:F22) -> 39
A25: Execution Status
A26: Status | B26: Count | D26: Metric | E26: Value
A27: Not Run | B27: =COUNTIF('10_Print_Functionality'!K:K,"Not Run")+COUNTIF('20_Copy_Functionality'!K:K,"Not Run")+COUNTIF('30_Scan_Functionality'!K:K,"Not Run")+COUNTIF('40_Network_Connectivity'!K:K,"Not Run")+COUNTIF('50_Firmware_Configuration'!K:K,"Not Run")+COUNTIF('60_Paper_Handling_Media'!K:K,"Not Run")+COUNTIF('70_UI_Control_Panel'!K:K,"Not Run")+COUNTIF('80_Security_Access'!K:K,"Not Run")+COUNTIF('90_Monitoring_Alerts'!K:K,"Not Run")+COUNTIF('100_Performance_Reliability'!K:K,"Not Run")+COUNTIF('110_E2E'!K:K,"Not Run") -> 60 | D27: Total Test Cases | E27: =C23 -> 60
A28: Pass | B28: =COUNTIF('10_Print_Functionality'!K:K,"Pass")+COUNTIF('20_Copy_Functionality'!K:K,"Pass")+COUNTIF('30_Scan_Functionality'!K:K,"Pass")+COUNTIF('40_Network_Connectivity'!K:K,"Pass")+COUNTIF('50_Firmware_Configuration'!K:K,"Pass")+COUNTIF('60_Paper_Handling_Media'!K:K,"Pass")+COUNTIF('70_UI_Control_Panel'!K:K,"Pass")+COUNTIF('80_Security_Access'!K:K,"Pass")+COUNTIF('90_Monitoring_Alerts'!K:K,"Pass")+COUNTIF('100_Performance_Reliability'!K:K,"Pass")+COUNTIF('110_E2E'!K:K,"Pass") -> 0 | D28: Executed Cases | E28: =B28+B29+B30 -> 0
A29: Fail | B29: =COUNTIF('10_Print_Functionality'!K:K,"Fail")+COUNTIF('20_Copy_Functionality'!K:K,"Fail")+COUNTIF('30_Scan_Functionality'!K:K,"Fail")+COUNTIF('40_Network_Connectivity'!K:K,"Fail")+COUNTIF('50_Firmware_Configuration'!K:K,"Fail")+COUNTIF('60_Paper_Handling_Media'!K:K,"Fail")+COUNTIF('70_UI_Control_Panel'!K:K,"Fail")+COUNTIF('80_Security_Access'!K:K,"Fail")+COUNTIF('90_Monitoring_Alerts'!K:K,"Fail")+COUNTIF('100_Performance_Reliability'!K:K,"Fail")+COUNTIF('110_E2E'!K:K,"Fail") -> 0 | D29: Execution % | E29: =IF(E27=0,0,E28/E27) -> 0
A30: Blocked | B30: =COUNTIF('10_Print_Functionality'!K:K,"Blocked")+COUNTIF('20_Copy_Functionality'!K:K,"Blocked")+COUNTIF('30_Scan_Functionality'!K:K,"Blocked")+COUNTIF('40_Network_Connectivity'!K:K,"Blocked")+COUNTIF('50_Firmware_Configuration'!K:K,"Blocked")+COUNTIF('60_Paper_Handling_Media'!K:K,"Blocked")+COUNTIF('70_UI_Control_Panel'!K:K,"Blocked")+COUNTIF('80_Security_Access'!K:K,"Blocked")+COUNTIF('90_Monitoring_Alerts'!K:K,"Blocked")+COUNTIF('100_Performance_Reliability'!K:K,"Blocked")+COUNTIF('110_E2E'!K:K,"Blocked") -> 0 | D30: Pass Rate | E30: =IF(E28=0,0,B28/E28) -> 0
D31: Fail Rate | E31: =IF(E28=0,0,B29/E28) -> 0

Sheet Lists
A1: Not Run | B1: Critical | C1: Yes | D1: Positive
A2: Pass | B2: High | C2: Later | D2: Negative
A3: Fail | B3: Medium | C3: No | D3: Regression
A4: Blocked | B4: Low | D4: Integration
D5: Security
D6: E2E
D7: Performance
D8: Usability

Sheet 10_Print_Functionality
A1: Update the Status and Notes columns during execution. Summary KPIs and counts refresh automatically.
A2: TC_ID | B2: Module | C2: Scenario | D2: Preconditions | E2: Steps | F2: Test Data | G2: Expected Result | H2: Priority | I2: Type | J2: Automation Candidate | K2: Status | L2: Notes
A3: PRT-001 | B3: Print Functionality | C3: Local USB print job completes using default settings | D3: Printer is powered on, idle, and USB host port is enabled. | E3: 1. Insert USB storage with supported PDF file 2. Select file from local print menu 3. Start job using default settings | F3: PDF file: invoice_2pages.pdf | G3: Printer accepts the job, prints both pages correctly, and returns to Ready state. | H3: High | I3: Positive | J3: Later | K3: Not Run | L3: Baseline local print
A4: PRT-002 | B4: Print Functionality | C4: Network print job submitted over IPP is received and printed | D4: Printer is connected to LAN and discoverable from a workstation. | E4: 1. Add printer from workstation 2. Send 3-page document via IPP 3. Monitor printer queue and output | F4: Word document: test_packet_3pages.docx | G4: Job appears in queue, renders correctly, and final output order matches source document. | H4: Critical | I4: Integration | J4: Yes | K4: Not Run | L4: Driverless print coverage
A5: PRT-003 | B5: Print Functionality | C5: Unsupported file type from USB is rejected with clear feedback | D5: Printer UI is available and USB local print is enabled. | E5: 1. Insert USB storage with unsupported file 2. Select unsupported file 3. Attempt local print | F5: Unsupported file: archive.zip | G5: Printer blocks the job, displays a clear unsupported-format message, and does not hang. | H5: High | I5: Negative | J5: Yes | K5: Not Run | L5: Input validation
A6: PRT-004 | B6: Print Functionality | C6: Duplex print honors long-edge binding setting | D6: Printer has duplex unit installed and paper tray loaded with A4 plain paper. | E6: 1. Submit 4-page document 2. Select duplex long-edge option 3. Print and inspect output | F6: PDF file: duplex_sample_4pages.pdf | G6: All pages print front/back in the correct page order and orientation for long-edge binding. | H6: High | I6: Regression | J6: Later | K6: Not Run | L6: Duplex behavior
A7: PRT-005 | B7: Print Functionality | C7: Large raster image print does not crash or reset the device | D7: Printer has sufficient memory and is idle. | E7: 1. Submit a high-resolution image file 2. Monitor device responsiveness during rendering 3. Confirm job completion | F7: Image file: poster_600dpi_50MB.tif | G7: Printer remains responsive, completes the job without firmware reset, and logs no fatal rendering error. | H7: Critical | I7: Performance | J7: Later | K7: Not Run | L7: Memory/render stress
A8: PRT-006 | B8: Print Functionality | C8: Cancelling an active print job stops output gracefully | D8: A multi-page print job is already printing. | E8: 1. Start 20-page job 2. Wait until page 5 prints 3. Cancel job from control panel | F8: PDF file: long_job_20pages.pdf | G8: Active job stops gracefully, queue is cleared or marked cancelled, and subsequent jobs can be printed normally. | H8: High | I8: Usability | J8: Yes | K8: Not Run | L8: Cancel flow

Sheet 20_Copy_Functionality
A1: Update the Status and Notes columns during execution. Summary KPIs and counts refresh automatically.
A2: TC_ID | B2: Module | C2: Scenario | D2: Preconditions | E2: Steps | F2: Test Data | G2: Expected Result | H2: Priority | I2: Type | J2: Automation Candidate | K2: Status | L2: Notes
A3: CPY-001 | B3: Copy Functionality | C3: Single-page copy from flatbed reproduces original clearly | D3: Printer is powered on and scanner glass is clean. | E3: 1. Place original on flatbed 2. Press Copy 3. Use default settings | F3: Original document: text_sample_A4 | G3: Copy completes with readable text, correct margins, and no skew or clipping. | H3: High | I3: Positive | J3: Later | K3: Not Run | L3: Baseline copy
A4: CPY-002 | B4: Copy Functionality | C4: ADF multi-page copy preserves page count and order | D4: ADF is loaded with three pages and no paper jam is present. | E4: 1. Load 3 sheets into ADF 2. Select Copy 3. Start job | F4: ADF set: contract_pages_1_to_3 | G4: All 3 pages are copied in correct order with no missing or duplicated page. | H4: Critical | I4: Integration | J4: Later | K4: Not Run | L4: ADF feed order
A5: CPY-003 | B5: Copy Functionality | C5: Multiple copy count prints requested number only once per source page | D5: Printer is idle and has enough paper. | E5: 1. Place single-page original 2. Set copies to 5 3. Start copy job | F5: Single-page original, copies=5 | G5: Exactly 5 output copies are produced and device does not exceed requested quantity. | H5: High | I5: Regression | J5: Yes | K5: Not Run | L5: Copy counter
A6: CPY-004 | B6: Copy Functionality | C6: Copy reduction to 50 percent scales output correctly | D6: Printer is idle and source document has visible edge markers. | E6: 1. Place original on flatbed 2. Set reduce/enlarge to 50% 3. Start copy | F6: Scaling target = 50% | G6: Output content is reduced uniformly, remains legible, and stays centered within printable area. | H6: Medium | I6: Positive | J6: Later | K6: Not Run | L6: Scaling feature
A7: CPY-005 | B7: Copy Functionality | C7: Cover open during copy causes safe pause and recovery message | D7: Copy job is started from flatbed or ADF. | E7: 1. Start copy job 2. Open scanner cover during processing if safely supported in simulation 3. Close cover and follow prompt | F7: Copy job in progress | G7: Device enters safe error state or pause, shows operator guidance, and recovers without crash after corrective action. | H7: High | I7: Negative | J7: No | K7: Not Run | L7: Mechanical interruption
A8: CPY-006 | B8: Copy Functionality | C8: Blank-page copy from ADF does not create false jam condition | D8: ADF has one blank page loaded. | E8: 1. Load blank page into ADF 2. Start copy 3. Observe feed and status | F8: Blank A4 page | G8: Page feeds normally, copy output is blank as expected, and no false jam or sensor error is raised. | H8: Medium | I8: Regression | J8: Later | K8: Not Run | L8: Sensor robustness

Sheet 30_Scan_Functionality
A1: Update the Status and Notes columns during execution. Summary KPIs and counts refresh automatically.
A2: TC_ID | B2: Module | C2: Scenario | D2: Preconditions | E2: Steps | F2: Test Data | G2: Expected Result | H2: Priority | I2: Type | J2: Automation Candidate | K2: Status | L2: Notes
A3: SCN-001 | B3: Scan Functionality | C3: Scan to USB creates file in selected format | D3: USB storage is inserted and writable. | E3: 1. Place original on flatbed 2. Choose Scan to USB 3. Select PDF 4. Start scan | F3: Original document: receipt_A5 | G3: Scanner creates the PDF file on USB with readable image and expected filename or timestamp. | H3: High | I3: Positive | J3: Later | K3: Not Run | L3: Local scan output
A4: SCN-002 | B4: Scan Functionality | C4: Scan to network folder succeeds with valid SMB credentials | D4: Network share exists and credentials are correct. | E4: 1. Configure SMB destination 2. Place document in ADF 3. Start scan to folder | F4: SMB path, valid username/password | G4: Scanned file is delivered to target folder, status shows success, and metadata such as filename/date is correct. | H4: Critical | I4: Integration | J4: Later | K4: Not Run | L4: Scan-to-folder
A5: SCN-003 | B5: Scan Functionality | C5: Invalid network folder credentials are rejected without storing secrets in plain view | D5: Printer has scan-to-folder feature enabled. | E5: 1. Configure SMB destination with wrong password 2. Start scan 3. Review UI and logs | F5: Invalid password | G5: Job fails with authentication error, no document is sent, and masked credentials remain protected in UI/logs. | H5: Critical | I5: Security | J5: Later | K5: Not Run | L5: Credential handling
A6: SCN-004 | B6: Scan Functionality | C6: ADF scan of mixed 5-page packet preserves page count and orientation | D6: ADF is loaded with 5 pages of the same size. | E6: 1. Load 5-page packet 2. Start scan to email or folder 3. Open resulting file | F6: Packet: pages_1_to_5 | G6: Output file contains all 5 pages in order with correct orientation and no page skipped. | H6: High | I6: Regression | J6: Later | K6: Not Run | L6: ADF scan continuity
A7: SCN-005 | B7: Scan Functionality | C7: Selected resolution and color mode are reflected in output | D7: Printer supports selectable DPI and color modes. | E7: 1. Scan same source at 200 dpi grayscale 2. Scan again at 300 dpi color 3. Compare file properties | F7: Resolution/color combinations | G7: Generated files reflect selected mode and resolution differences in metadata and visual output. | H7: Medium | I7: Positive | J7: Yes | K7: Not Run | L7: Settings persistence
A8: SCN-006 | B8: Scan Functionality | C8: Scan job can be cancelled before final file commit | D8: Scan destination is reachable and job is in progress. | E8: 1. Start multi-page scan job 2. Cancel before completion 3. Inspect destination and device state | F8: 10-page ADF packet | G8: Partial output is not incorrectly committed as complete, job is marked cancelled, and scanner returns to Ready state. | H8: High | I8: Negative | J8: Yes | K8: Not Run | L8: Cancel behavior

Sheet 40_Network_Connectivity
A1: Update the Status and Notes columns during execution. Summary KPIs and counts refresh automatically.
A2: TC_ID | B2: Module | C2: Scenario | D2: Preconditions | E2: Steps | F2: Test Data | G2: Expected Result | H2: Priority | I2: Type | J2: Automation Candidate | K2: Status | L2: Notes
A3: NET-001 | B3: Network Connectivity | C3: Device joins Wi-Fi network with valid WPA2 credentials | D3: Printer Wi-Fi radio is enabled and test SSID is available. | E3: 1. Open wireless setup 2. Enter valid SSID/password 3. Save and connect | F3: SSID: QA_LAB_24G, valid password | G3: Printer obtains network connectivity, displays IP address, and remains reachable from test workstation. | H3: Critical | I3: Integration | J3: No | K3: Not Run | L3: Wireless onboarding
A4: NET-002 | B4: Network Connectivity | C4: Invalid Wi-Fi password does not create false-connected state | D4: Test SSID is available. | E4: 1. Enter correct SSID with wrong password 2. Attempt connection 3. Observe status | F4: SSID: QA_LAB_24G, invalid password | G4: Connection fails clearly, device does not display connected state, and previous stable config remains intact or recoverable. | H4: High | I4: Negative | J4: No | K4: Not Run | L4: Auth failure
A5: NET-003 | B5: Network Connectivity | C5: DHCP lease renewal does not interrupt idle services or orphan stale IP | D5: Printer is connected via Ethernet and DHCP server is available. | E5: 1. Trigger DHCP renewal from network or reboot sequence 2. Verify new/retained IP 3. Check printer discovery | F5: DHCP environment | G5: Printer remains discoverable after renewal and reports accurate network settings. | H5: High | I5: Regression | J5: No | K5: Not Run | L5: IP lease stability
A6: NET-004 | B6: Network Connectivity | C6: Print job pauses or fails gracefully when LAN cable is removed mid-transfer | D6: Network print job is actively spooling over Ethernet. | E6: 1. Start large network print job 2. Remove Ethernet link during transfer 3. Reconnect link and observe outcome | F6: Large PDF over Ethernet | G6: Device and client handle network loss gracefully with retry, pause, or clear failure message; firmware does not freeze. | H6: Critical | I6: Negative | J6: Later | K6: Not Run | L6: Mid-job disconnect
A7: NET-005 | B7: Network Connectivity | C7: WS-Print or IPP discovery exposes accurate device capabilities to host | D7: Printer is on same subnet as test workstation. | E7: 1. Discover printer from host 2. Inspect reported capabilities 3. Compare with configured hardware | F7: Device capabilities: duplex, color, trays | G7: Host sees accurate capabilities and no unsupported option is falsely advertised. | H7: High | I7: Integration | J7: Later | K7: Not Run | L7: Discovery/capability sync
A8: NET-006 | B8: Network Connectivity | C8: Duplicate IP conflict is surfaced with actionable error handling | D8: Another device is configured with the same static IP. | E8: 1. Set printer to conflicting static IP 2. Reconnect printer to network 3. Observe UI, logs, and reachability | F8: Conflicting static IP address | G8: Printer detects or surfaces connectivity issue, avoids unstable connected state, and provides actionable network error indication. | H8: Medium | I8: Negative | J8: No | K8: Not Run | L8: Conflict handling

Sheet 50_Firmware_Configuration
A1: Update the Status and Notes columns during execution. Summary KPIs and counts refresh automatically.
A2: TC_ID | B2: Module | C2: Scenario | D2: Preconditions | E2: Steps | F2: Test Data | G2: Expected Result | H2: Priority | I2: Type | J2: Automation Candidate | K2: Status | L2: Notes
A3: FWM-001 | B3: Firmware & Configuration | C3: Signed firmware package installs successfully from approved source | D3: Printer is on stable power and approved firmware package is available. | E3: 1. Open firmware update menu 2. Upload or select approved package 3. Start installation 4. Reboot if prompted | F3: Firmware package: aio_v1.2.3_signed.bin | G3: Firmware validates signature, installs successfully, reports new version, and preserves baseline configuration unless release notes state otherwise. | H3: Critical | I3: Positive | J3: No | K3: Not Run | L3: Standard upgrade
A4: FWM-002 | B4: Firmware & Configuration | C4: Tampered or invalid firmware package is rejected before install | D4: Printer is on current stable firmware. | E4: 1. Attempt update using tampered package 2. Confirm validation result | F4: Firmware package: aio_v1.2.3_tampered.bin | G4: Device rejects package, makes no firmware changes, and records validation failure in logs without bricking the unit. | H4: Critical | I4: Security | J4: Yes | K4: Not Run | L4: Package integrity
A5: FWM-003 | B5: Firmware & Configuration | C5: Power interruption during firmware install triggers safe recovery path | D5: Recovery image or rollback mechanism is available in simulation. | E5: 1. Start firmware installation 2. Simulate power loss during write phase 3. Restore power and boot device | F5: Firmware package plus forced power cut | G5: Printer boots into recovery or rollback path, avoids corrupted half-installed state, and allows restoration to known-good firmware. | H5: Critical | I5: Negative | J5: No | K5: Not Run | L5: Resilience
A6: FWM-004 | B6: Firmware & Configuration | C6: User settings persist after minor firmware upgrade | D6: Printer has non-default network, scan, and energy settings configured. | E6: 1. Record current settings 2. Install minor approved firmware 3. Reboot and compare settings | F6: Configured Wi-Fi, scan defaults, sleep timer | G6: Supported user settings persist correctly after upgrade and device remains operational. | H6: High | I6: Regression | J6: Later | K6: Not Run | L6: Config persistence
A7: FWM-005 | B7: Firmware & Configuration | C7: Factory reset clears user settings but preserves secure recovery and onboarding readiness | D7: Printer has custom admin password and saved destinations configured. | E7: 1. Perform factory reset from service/admin menu 2. Reboot 3. Review settings and onboarding flow | F7: Configured admin password and destinations | G7: User-configured settings are removed as designed, device returns to initial setup state, and no stale credentials remain. | H7: High | I7: Security | J7: No | K7: Not Run | L7: Reset behavior
A8: FWM-006 | B8: Firmware & Configuration | C8: Unsupported downgrade path is blocked or explicitly controlled | D8: Printer is on newer firmware than downgrade package. | E8: 1. Attempt firmware downgrade using older package 2. Observe prompts and logs | F8: Firmware package older than installed version | G8: System blocks downgrade or requires explicit service procedure according to policy, with no unstable partial install. | H8: Medium | I8: Negative | J8: No | K8: Not Run | L8: Version control

Sheet 60_Paper_Handling_Media
A1: Update the Status and Notes columns during execution. Summary KPIs and counts refresh automatically.
A2: TC_ID | B2: Module | C2: Scenario | D2: Preconditions | E2: Steps | F2: Test Data | G2: Expected Result | H2: Priority | I2: Type | J2: Automation Candidate | K2: Status | L2: Notes
A3: MED-001 | B3: Paper Handling & Media | C3: Empty tray condition is detected before print start | D3: Selected tray is empty and printer is Ready. | E3: 1. Submit print job that targets empty tray 2. Observe status | F3: A4 print job with empty Tray 1 | G3: Printer detects out-of-paper state, stops before image transfer, and prompts for media load without corrupting the job. | H3: High | I3: Negative | J3: Yes | K3: Not Run | L3: Pre-feed paper check
A4: MED-002 | B4: Paper Handling & Media | C4: Paper jam during print is reported with recoverable guidance | D4: Printer is printing multi-page job and jam scenario is simulated. | E4: 1. Start multi-page print 2. Simulate jam in feed path 3. Clear jam 4. Resume or reprint | F4: 10-page job with jam on page 3 | G4: Device shows jam location guidance, preserves safe state, and resumes/restarts according to design without crash. | H4: Critical | I4: Negative | J4: No | K4: Not Run | L4: Jam recovery
A5: MED-003 | B5: Paper Handling & Media | C5: Manual feed tray accepts envelope media when selected correctly | D5: Manual feed tray and envelope media are available. | E5: 1. Submit envelope print job 2. Select manual feed and envelope media type 3. Print | F5: Envelope #10 / DL | G5: Printer prompts for manual feed as needed and prints envelope without skew or unsupported-media error. | H5: Medium | I5: Positive | J5: Later | K5: Not Run | L5: Special media
A6: MED-004 | B6: Paper Handling & Media | C6: Mismatched paper size between job and tray triggers clear prompt | D6: Tray loaded with Letter while job requests A4. | E6: 1. Send A4 job 2. Ensure tray contains Letter 3. Observe prompt options | F6: A4 job, Letter media loaded | G6: Device prompts for load/override/cancel according to policy and does not silently misprint on wrong size without warning. | H6: High | I6: Integration | J6: Yes | K6: Not Run | L6: Size mismatch
A7: MED-005 | B7: Paper Handling & Media | C7: Low toner or ink warning appears before depletion threshold is exceeded | D7: Consumable simulation or test cartridge state is available. | E7: 1. Trigger low consumable threshold 2. Review panel and status interface | F7: Low toner/ink simulated state | G7: Warning appears consistently in UI/status channel while printing remains possible until critical threshold. | H7: Medium | I7: Regression | J7: No | K7: Not Run | L7: Consumable alerts
A8: MED-006 | B8: Paper Handling & Media | C8: Output tray full condition prevents uncontrolled spill or silent job loss | D8: Output tray full sensor state can be simulated. | E8: 1. Print continuous set until output tray full state is reached 2. Observe handling | F8: Large print run | G8: Device pauses or surfaces output-full condition appropriately and protects job integrity until user clears output path. | H8: Medium | I8: Negative | J8: No | K8: Not Run | L8: Output capacity

Sheet 70_UI_Control_Panel
A1: Update the Status and Notes columns during execution. Summary KPIs and counts refresh automatically.
A2: TC_ID | B2: Module | C2: Scenario | D2: Preconditions | E2: Steps | F2: Test Data | G2: Expected Result | H2: Priority | I2: Type | J2: Automation Candidate | K2: Status | L2: Notes
A3: UI-001 | B3: UI & Control Panel | C3: Home screen loads all primary functions without missing icons or labels | D3: Printer has completed boot sequence. | E3: 1. Observe home screen after Ready state 2. Review Copy/Print/Scan/Network/Admin entries | F3: Home screen | G3: Primary functions are visible, readable, and selectable without rendering issues or missing assets. | H3: High | I3: Usability | J3: No | K3: Not Run | L3: Baseline UI
A4: UI-002 | B4: UI & Control Panel | C4: Touch response remains accurate across menu navigation | D4: Touch panel calibration is nominal. | E4: 1. Open settings and scan menus 2. Select several items near screen edges 3. Return home | F4: Touch panel navigation | G4: Touches register accurately, no ghost taps occur, and navigation remains stable. | H4: High | I4: Regression | J4: No | K4: Not Run | L4: Input responsiveness
A5: UI-003 | B5: UI & Control Panel | C5: Invalid admin PIN attempt shows error without exposing secure menu | D5: Admin menu is protected by PIN. | E5: 1. Open admin menu 2. Enter incorrect PIN 3. Observe outcome | F5: Invalid PIN | G5: Access is denied, secure menu remains hidden, and UI does not reveal sensitive configuration details. | H5: Critical | I5: Security | J5: Yes | K5: Not Run | L5: Secure access
A6: UI-004 | B6: UI & Control Panel | C6: Language switch updates labels consistently after confirmation | D6: Multiple UI languages are installed. | E6: 1. Change display language 2. Reopen major menus 3. Reboot if required and verify persistence | F6: Language: English to Filipino | G6: UI labels switch consistently, do not overlap/truncate badly, and selected language persists as designed. | H6: Medium | I6: Usability | J6: Later | K6: Not Run | L6: Localization
A7: UI-005 | B7: UI & Control Panel | C7: Sleep and wake transitions preserve control-panel responsiveness | D7: Energy saver is enabled. | E7: 1. Allow printer to enter sleep 2. Wake using panel or incoming job 3. Navigate menus | F7: Sleep timer active | G7: Device wakes within expected time and panel remains responsive without frozen or partially drawn screens. | H7: High | I7: Performance | J7: Later | K7: Not Run | L7: Power state UX

Sheet 80_Security_Access
A1: Update the Status and Notes columns during execution. Summary KPIs and counts refresh automatically.
A2: TC_ID | B2: Module | C2: Scenario | D2: Preconditions | E2: Steps | F2: Test Data | G2: Expected Result | H2: Priority | I2: Type | J2: Automation Candidate | K2: Status | L2: Notes
A3: SEC-001 | B3: Security & Access | C3: Administrative web console requires authentication before configuration access | D3: Embedded web server is enabled and reachable. | E3: 1. Open admin web URL 2. Attempt access without login | F3: Admin URL | G3: Unauthenticated user is redirected to login or denied access; configuration data is not exposed. | H3: Critical | I3: Security | J3: Yes | K3: Not Run | L3: Web admin auth
A4: SEC-002 | B4: Security & Access | C4: Session timeout logs out idle authenticated admin session | D4: Admin user is logged into web console. | E4: 1. Log in to admin console 2. Leave session idle beyond timeout 3. Attempt privileged action | F4: Idle authenticated session | G4: Session expires as configured and re-authentication is required before further privileged actions. | H4: High | I4: Security | J4: Yes | K4: Not Run | L4: Session management
A5: SEC-003 | B5: Security & Access | C5: TLS-enabled management endpoint rejects weak or invalid certificate path | D5: HTTPS management is enabled and certificate validation policy is set. | E5: 1. Connect with weak/invalid certificate scenario in lab 2. Inspect client behavior and printer settings | F5: Invalid/expired certificate scenario | G5: Connection behavior matches policy, invalid certificate is surfaced appropriately, and sensitive data is not transmitted insecurely. | H5: Medium | I5: Security | J5: No | K5: Not Run | L5: Transport security
A6: SEC-004 | B6: Security & Access | C6: Stored scan destination credentials are masked in UI and export views | D6: At least one scan destination is configured. | E6: 1. Open destination configuration 2. Inspect edit/view/export screens | F6: Stored SMB/email credentials | G6: Secrets remain masked or protected and are not shown in clear text to non-privileged users. | H6: Critical | I6: Security | J6: Later | K6: Not Run | L6: Secret masking
A7: SEC-005 | B7: Security & Access | C7: Factory reset removes saved user credentials and address book entries | D7: Printer has saved destinations, address book, and admin session history. | E7: 1. Confirm saved credentials/address book exist 2. Perform factory reset 3. Recheck storage and logs | F7: Saved SMB/email destinations | G7: Sensitive user data is removed according to policy and device returns to clean onboarding state. | H7: Critical | I7: Security | J7: No | K7: Not Run | L7: Data sanitization

Sheet 90_Monitoring_Alerts
A1: Update the Status and Notes columns during execution. Summary KPIs and counts refresh automatically.
A2: TC_ID | B2: Module | C2: Scenario | D2: Preconditions | E2: Steps | F2: Test Data | G2: Expected Result | H2: Priority | I2: Type | J2: Automation Candidate | K2: Status | L2: Notes
A3: MON-001 | B3: Monitoring & Alerts | C3: Status page reports Ready, Busy, and Error states consistently | D3: Status interface (panel, web, or API) is available. | E3: 1. Capture state when idle 2. Start job and observe Busy 3. Trigger recoverable error and observe Error | F3: Idle/job/error states | G3: Reported device state changes match actual physical behavior with no stale or contradictory state. | H3: High | I3: Integration | J3: Yes | K3: Not Run | L3: State accuracy
A4: MON-002 | B4: Monitoring & Alerts | C4: Job history records print, copy, and scan jobs with stable identifiers | D4: History view is enabled and jobs can be executed. | E4: 1. Run one print, one copy, one scan job 2. Open job history | F4: Three completed jobs | G4: History shows each job with stable ID, type, timestamp, and terminal status. | H4: High | I4: Regression | J4: Yes | K4: Not Run | L4: Audit trail
A5: MON-003 | B5: Monitoring & Alerts | C5: Consumable alert is reflected both on panel and management interface | D5: Low consumable state can be simulated. | E5: 1. Trigger low toner/ink alert 2. Check panel 3. Check web/API status | F5: Low consumable simulated state | G5: Alert appears consistently across local and remote status surfaces within expected sync interval. | H5: Medium | I5: Integration | J5: Yes | K5: Not Run | L5: Cross-channel alerting
A6: MON-004 | B6: Monitoring & Alerts | C6: Recoverable fault clears from status after operator resolution | D6: Jam or cover-open condition can be simulated. | E6: 1. Trigger recoverable fault 2. Clear condition 3. Refresh status surfaces | F6: Jam or cover-open event | G6: Fault is removed after resolution and printer returns to Ready without stale persistent alert. | H6: High | I6: Regression | J6: Yes | K6: Not Run | L6: Fault clear
A7: MON-005 | B7: Monitoring & Alerts | C7: Firmware event log stores update attempt result with timestamp | D7: Firmware update path is available. | E7: 1. Attempt one successful or failed update 2. Review logs/history | F7: Firmware event entry | G7: Event log records update attempt, result, and timestamp for service traceability. | H7: Medium | I7: Positive | J7: Later | K7: Not Run | L7: Service logs

Sheet 100_Performance_Reliability
A1: Update the Status and Notes columns during execution. Summary KPIs and counts refresh automatically.
A2: TC_ID | B2: Module | C2: Scenario | D2: Preconditions | E2: Steps | F2: Test Data | G2: Expected Result | H2: Priority | I2: Type | J2: Automation Candidate | K2: Status | L2: Notes
A3: PRF-001 | B3: Performance & Reliability | C3: Cold boot reaches Ready state within target threshold | D3: Printer is powered off and baseline environment is stable. | E3: 1. Power on device 2. Measure time until Ready state and key services available | F3: Cold boot condition | G3: Printer reaches Ready state within agreed threshold and no critical boot error is logged. | H3: High | I3: Performance | J3: No | K3: Not Run | L3: Boot KPI
A4: PRF-002 | B4: Performance & Reliability | C4: 50-page print run completes without reset or memory leak symptoms | D4: Printer has enough paper and consumables for continuous run. | E4: 1. Submit 50-page mixed-content job 2. Monitor device responsiveness and job completion | F4: Mixed 50-page PDF | G4: Printer completes the run without crash, reset, or severe responsiveness degradation. | H4: Critical | I4: Performance | J4: Later | K4: Not Run | L4: Sustained print
A5: PRF-003 | B5: Performance & Reliability | C5: Repeated scan jobs over 1 hour do not degrade throughput materially | D5: Printer is connected to scan destination and ADF is available. | E5: 1. Execute repeated scan jobs for one hour 2. Track completion times and errors | F5: Batch scan packet reused | G5: Scan throughput remains within tolerance and no cumulative firmware instability appears. | H5: High | I5: Performance | J5: Later | K5: Not Run | L5: Soak test
A6: PRF-004 | B6: Performance & Reliability | C6: Sleep-wake cycles repeated 20 times do not break network discoverability | D6: Printer is configured on network and sleep is enabled. | E6: 1. Trigger repeated sleep/wake cycles 2. Discover printer after each wake | F6: 20 sleep/wake iterations | G6: Device remains reachable and discoverable after repeated power-state transitions. | H6: High | I6: Regression | J6: Later | K6: Not Run | L6: Power-state reliability
A7: PRF-005 | B7: Performance & Reliability | C7: Simultaneous remote status polling and print activity does not starve UI | D7: Remote management polling is configured and printer is active. | E7: 1. Begin frequent status polling 2. Submit print job 3. Navigate control panel during job | F7: Status polling + active print job | G7: Device remains usable, status remains accurate, and no watchdog reset occurs under concurrent load. | H7: Medium | I7: Performance | J7: No | K7: Not Run | L7: Concurrency

Sheet 110_E2E
A1: Update the Status and Notes columns during execution. Summary KPIs and counts refresh automatically.
A2: TC_ID | B2: Module | C2: Scenario | D2: Preconditions | E2: Steps | F2: Test Data | G2: Expected Result | H2: Priority | I2: Type | J2: Automation Candidate | K2: Status | L2: Notes
A3: E2E-001 | B3: End-to-End | C3: Newly onboarded network printer can print, scan, and copy in same session | D3: Printer is factory-reset and test workstation/network are ready. | E3: 1. Perform initial network setup 2. Print a network job 3. Scan to folder 4. Run one copy job | F3: Onboarding credentials plus standard sample docs | G3: All core functions succeed end-to-end after first-time setup without requiring unsupported workarounds. | H3: Critical | I3: E2E | J3: No | K3: Not Run | L3: Core AIO journey
A4: E2E-002 | B4: End-to-End | C4: Firmware upgrade followed by regression smoke confirms core functions remain intact | D4: Approved upgrade package is available. | E4: 1. Record baseline version 2. Upgrade firmware 3. Run smoke: print, copy, scan, status check | F4: Firmware package + smoke files | G4: Printer upgrades successfully and core functions remain operational with expected settings and status reporting. | H4: Critical | I4: Regression | J4: Later | K4: Not Run | L4: Post-upgrade smoke
A5: E2E-003 | B5: End-to-End | C5: Jam recovery during mixed workload does not corrupt subsequent queued jobs | D5: Printer queue has multiple print/copy/scan tasks in sequence. | E5: 1. Start print job 2. Trigger jam 3. Clear jam 4. Continue with remaining jobs | F5: Mixed queued workload | G5: After recovery, queue integrity is preserved and later jobs execute or fail according to design without hidden corruption. | H5: High | I5: E2E | J5: No | K5: Not Run | L5: Queue resilience
A6: E2E-004 | B6: End-to-End | C6: Factory reset followed by reconfiguration restores service without stale user data | D6: Printer has prior admin setup and saved destinations. | E6: 1. Verify prior user data exists 2. Perform factory reset 3. Reconfigure network and one destination 4. Validate print/scan | F6: Preloaded credentials and address book | G6: Device returns to clean state, stale user data is absent, and reconfigured services operate normally. | H6: High | I6: E2E | J6: No | K6: Not Run | L6: Lifecycle coverage
